sphinx_new_tab_link/__init__.py
sphinx_new_tab_link/core.py
sphinx_new_tab_link/extras.py
sphinx_new_tab_link/roles.py
sphinx_new_tab_link-0.8.1.dist-info/licenses/LICENSE
sphinx_new_tab_link-0.8.1.dist-info/METADATA
sphinx_new_tab_link-0.8.1.dist-info/WHEEL
sphinx_new_tab_link-0.8.1.dist-info/top_level.txt
sphinx_new_tab_link-0.8.1.dist-info/RECORD
